{
  "is-c3-addon": true,
  "type": "plugin",
  "name": "Spine",
  "id": "Gritsenko_Spine",
  "version": "2.3.1",
  "author": "Mikal and Igor Gritsenko",
  "website": "https://gritsenko.github.io/c3_spine_plugin",
  "documentation": "https://gritsenko.github.io/c3_spine_plugin",
  "description": "Spine addon - render to textures",
  "editor-scripts": [
    "plugin.js",
    "type.js",
    "instance.js"
  ],
  "file-list": [
    "c3runtime/plugin.js",
    "c3runtime/type.js",
    "c3runtime/instance.js",
    "c3runtime/conditions.js",
    "c3runtime/actions.js",
    "c3runtime/expressions.js",
    "c3runtime/spine-webgl.js",
    "c3runtime/spine-draw.js",
    "c3runtime/spine-gl-cache.js",
    "c3runtime/spine-palette.js",
    "c3runtime/spine-bone-control.js",
    "lang/en-US.json",
    "aces.json",
    "addon.json",
    "icon.svg",
    "instance.js",
    "plugin.js",
    "type.js"
  ]
}
